audio_toolset/__init__.py
audio_toolset/audio_data.py
audio_toolset/channel.py
audio_toolset/oscillators.py
audio_toolset/plots.py
audio_toolset/util.py
audio_toolset/cli/__init__.py
audio_toolset/cli/decorators.py
audio_toolset/cli/helpers.py
audio_toolset/cli/main.py
audio_toolset/cli/structs.py
audio_toolset/constants/__init__.py
audio_toolset/constants/frequencies.py
audio_toolset/constants/math.py
audio_toolset/constants/plotting.py
audio_toolset/processing/__init__.py
audio_toolset/processing/dynamics.py
audio_toolset/processing/filters.py
audio_toolset/processing/gain.py
audio_toolset/processing/noise_reduction.py
audio_toolset-0.2.2.dist-info/METADATA
audio_toolset-0.2.2.dist-info/WHEEL
audio_toolset-0.2.2.dist-info/entry_points.txt
audio_toolset-0.2.2.dist-info/licenses/LICENSE
audio_toolset-0.2.2.dist-info/RECORD
