Metadata-Version: 2.4
Name: audio-toolset
Version: 0.2.2
Summary: Tools for processing audio signals
Project-URL: Repository, https://github.com/maxoshe/audio-toolset.git
Author-email: moshe-stanylov <maxoshe@gmail.com>
License-Expression: MIT
License-File: LICENSE
Classifier: Development Status :: 5 - Production/Stable
Classifier: Intended Audience :: Developers
Classifier: Intended Audience :: Science/Research
Classifier: Operating System :: OS Independent
Classifier: Programming Language :: Python
Classifier: Programming Language :: Python :: 3 :: Only
Classifier: Programming Language :: Python :: 3.10
Classifier: Programming Language :: Python :: 3.11
Classifier: Programming Language :: Python :: 3.12
Classifier: Topic :: Multimedia :: Sound/Audio
Requires-Python: <3.13,>=3.10
Requires-Dist: click>=8.2.1
Requires-Dist: numpy==2.0.1
Requires-Dist: plotly==5.23.0
Requires-Dist: pydantic>=2.11.7
Requires-Dist: scipy==1.13.1
Requires-Dist: soundfile==0.12.1
